machc/product/__init__.py
machc/product/entities/__init__.py
machc/product/entities/abs_product.py
machc/product/entities/category.py
machc/product/entities/dynamic_product.py
machc/product/entities/product.py
machc/product/entities/variant.py
machc/product/interactors/__init__.py
machc/product/interactors/user/__init__.py
machc/product/interactors/user/login.py
machc/product/interactors/user/registration.py
machc/product/interactors/user/exception/__init__.py
machc/product/interactors/user/exception/user_exception.py
machc/product/interactors/user/stud/__init__.py
machc/product/interactors/user/stud/user_login_service.py
machc/product/interactors/user/stud/user_registration_service.py
machc_product-0.0.2.dist-info/METADATA
machc_product-0.0.2.dist-info/WHEEL
machc_product-0.0.2.dist-info/top_level.txt
machc_product-0.0.2.dist-info/RECORD
