Metadata-Version: 2.4
Name: machc.product
Version: 0.0.2
Summary: The Product Domain Machc Library provides modular entities and interactors for managing e-commerce products, categories, and variants.
Author-email: Viktor Tovstyi <viktor.tovstyi@gmail.com>
Requires-Python: ==3.12.3
Requires-Dist: machc.base==0.0.2
